euler_maths/__init__.py
euler_maths/misc.py
euler_maths/prime.py
euler_maths-0.1.0.dist-info/METADATA
euler_maths-0.1.0.dist-info/WHEEL
euler_maths-0.1.0.dist-info/licenses/LICENSE
euler_maths-0.1.0.dist-info/RECORD
