Metadata-Version: 2.1
Name: euler_maths
Version: 0.1.0
Summary: A library of mathematical functions for Project Euler
Project-URL: Homepage, https://github.com/Luke943/Euler-Maths
Project-URL: Bug Tracker, https://github.com/Luke943/Euler-Maths/issues
Author-email: Luke Hartley <luke.hartley05@gmail.com>
License-File: LICENSE
Classifier: License :: OSI Approved :: MIT License
Classifier: Operating System :: OS Independent
Classifier: Programming Language :: Python :: 3
Requires-Python: >=3.8
Requires-Dist: bitarray
Requires-Dist: numpy
